git_big/__init__.py
git_big/filter.py
git_big/main.py
git_big/singleton.py
git_big/storage.py
git_big/windows.py
git_big-0.7.1.dist-info/METADATA
git_big-0.7.1.dist-info/RECORD
git_big-0.7.1.dist-info/WHEEL
git_big-0.7.1.dist-info/entry_points.txt
git_big-0.7.1.dist-info/top_level.txt
