Metadata-Version: 2.1
Name: git-big
Version: 0.7.1
Summary: Git Big is a command line extension to Git for managing Write Once Read Many (WORM) files.
Home-page: https://github.com/vertexai/git-big
Author: Vertex.AI
Author-email: UNKNOWN
License: Apache 2.0
Platform: UNKNOWN
Classifier: Development Status :: 4 - Beta
Classifier: Environment :: Console
Classifier: Intended Audience :: Developers
Classifier: License :: OSI Approved :: Apache Software License
Classifier: Natural Language :: English
Classifier: Operating System :: MacOS :: MacOS X
Classifier: Operating System :: Microsoft :: Windows :: Windows 10
Classifier: Operating System :: POSIX :: Linux
Classifier: Programming Language :: Python :: 2.7
Classifier: Programming Language :: Python :: 3.6
Classifier: Topic :: Software Development :: Version Control
Classifier: Topic :: Utilities
Requires-Dist: apache-libcloud (==1.5.0)
Requires-Dist: boto3
Requires-Dist: certifi
Requires-Dist: click
Requires-Dist: lockfile
Requires-Dist: progressbar2
Requires-Dist: six
Requires-Dist: jaraco.windows; platform_system == "Windows"
Requires-Dist: pywin32; platform_system == "Windows"
